{
  "news": [
    {
      "title": "이찬진 \"ETF 거짓·과장광고 엄중…'복붙' 공시도 뿌리 뽑아야\"",
      "url": "https://n.news.naver.com/mnews/article/648/0000048857"
    },
    {
      "title": "7월 1~10일 수출 298억달러, ‘역대 최대’… 반도체 193% 증가",
      "url": "https://n.news.naver.com/mnews/article/366/0001178680"
    },
    {
      "title": "2030년 재생에너지 100GW…AI·반도체 전력망 선제 구축",
      "url": "https://n.news.naver.com/mnews/article/119/0003110918"
    },
    {
      "title": "구윤철 \"2030년까지 청년 일자리 20만 개 창출‥공공임대 우선 배정\"",
      "url": "https://n.news.naver.com/mnews/article/214/0001511343"
    },
    {
      "title": "구미시 \"오뚜기라면 품고 라면도시 위상 높인다\"",
      "url": "https://n.news.naver.com/mnews/article/008/0005385306"
    },
    {
      "title": "\"지각비 냈어요\"…6월 팔린 아파트 절반 이상이 '상승 거래'",
      "url": "https://n.news.naver.com/mnews/article/008/0005385155"
    },
    {
      "title": "현대차 노조, 사흘간 부분파업 돌입…2년 연속 생산 차질",
      "url": "https://n.news.naver.com/mnews/article/092/0002430334"
    },
    {
      "title": "홈플러스 “운영자금 고갈”…오늘부터 전국 대형마트 휴업",
      "url": "https://n.news.naver.com/mnews/article/020/0003733443"
    },
    {
      "title": "“과거 사이클과 다른 장기 호황”… 한은, 반도체 고점론 일축",
      "url": "https://n.news.naver.com/mnews/article/005/0001860741"
    },
    {
      "title": "동영상뉴스",
      "url": "https://n.news.naver.com/mnews/article/056/0012216589"
    }
  ],
  "stocks": {
    "kospi": {
      "value": 7475.94,
      "change": 0.0,
      "change_pct": 0.0
    },
    "kosdaq": {
      "value": 837.43,
      "change": 0.0,
      "change_pct": 0.0
    },
    "nasdaq": {
      "value": 25873.18,
      "change": -408.43,
      "change_pct": -1.55
    },
    "usdkrw": {
      "value": 1497.02,
      "change": -8.89,
      "change_pct": -0.59
    }
  },
  "gold": {
    "price_usd": 4008.7,
    "price_krw": 6001104,
    "change": 0.0,
    "change_pct": 0.0
  },
  "updated": "2026-07-14 06:41",
  "error": null
}